lq_feishu_lark/__init__.py
lq_feishu_lark/home.py
lq_feishu_lark/api/__init__.py
lq_feishu_lark/api/sheets/__init__.py
lq_feishu_lark/api/sheets/request/__init__.py
lq_feishu_lark/api/sheets/request/get_spreadsheet_sheet_value_request.py
lq_feishu_lark/api/sheets/response/__init__.py
lq_feishu_lark/api/sheets/response/get_spreadsheet_sheet_value_response.py
lq_feishu_lark-0.0.2.dist-info/METADATA
lq_feishu_lark-0.0.2.dist-info/WHEEL
lq_feishu_lark-0.0.2.dist-info/top_level.txt
lq_feishu_lark-0.0.2.dist-info/RECORD
