Metadata-Version: 2.1
Name: lq-feishu-lark
Version: 0.0.2
Summary: 飞书扩展库
Home-page: https://gitee.com/my/my
Author: lant
Author-email: lant@163.com
License: UNKNOWN
Platform: UNKNOWN
Classifier: Programming Language :: Python :: 3
Classifier: License :: OSI Approved :: MIT License
Classifier: Operating System :: OS Independent
Requires-Python: >=3.6
